mcp_server_rememberizer/__init__.py
mcp_server_rememberizer/server.py
mcp_server_rememberizer/utils.py
mcp_server_rememberizer-0.1.6.dist-info/METADATA
mcp_server_rememberizer-0.1.6.dist-info/WHEEL
mcp_server_rememberizer-0.1.6.dist-info/entry_points.txt
mcp_server_rememberizer-0.1.6.dist-info/licenses/LICENSE
mcp_server_rememberizer-0.1.6.dist-info/RECORD
