Metadata-Version: 2.4
Name: mcp-server-rememberizer
Version: 0.1.6
Summary: A Model Context Protocol server for interacting with Rememberizer's document and knowledge management API. This server enables Large Language Models to search, retrieve, and manage documents and integrations through Rememberizer.
Author-email: Rememberizer <support@rememberizer.ai>
License-File: LICENSE
Requires-Python: >=3.11
Requires-Dist: httpx>=0.27.2
Requires-Dist: mcp>=1.0.0
Requires-Dist: python-dotenv>=1.0.1
